_hierarchical_umap.cpython-38-darwin.so
humap/__init__.py
humap/humap.py
humap-0.2.8.dist-info/LICENSE
humap-0.2.8.dist-info/METADATA
humap-0.2.8.dist-info/WHEEL
humap-0.2.8.dist-info/top_level.txt
humap-0.2.8.dist-info/RECORD
