Metadata-Version: 2.1
Name: humap
Version: 0.2.8
Summary: Hierarchical Uniform Manifold Approximation and Projection
Home-page: https://github.com/wilsonjr/humap
Author: Wilson E. Marcílio-Jr
Author-email: wilson_jr@outlook.com
License: MIT
License-File: LICENSE
Provides-Extra: test
Requires-Dist: pytest ; extra == 'test'
